Metadata-Version: 1.2
Name: jmesobj
Version: 0.0.1.dev1
Summary: JMESPath-powered data container ideal for JSON payloads.
Home-page: https://github.com/rmax/jmesobj
Author: R Max Espinoza
Author-email: me@rmax.io
License: MIT
Project-URL: Source, https://github.com/rmax/jmesobj
Project-URL: Tracker, https://github.com/rmax/jmesobj/issues
Platform: UNKNOWN
Classifier: Development Status :: 2 - Pre-Alpha
Classifier: Environment :: Web Environment
Classifier: Framework :: Django
Classifier: Intended Audience :: Developers
Classifier: License :: OSI Approved :: MIT License
Classifier: Operating System :: OS Independent
Classifier: Programming Language :: Python
Classifier: Programming Language :: Python :: 3 :: Only
Classifier: Programming Language :: Python :: 3.7
Classifier: Programming Language :: Python :: 3.8
Classifier: Topic :: Software Development :: Libraries :: Python Modules
Requires-Python: >=3.7
